nqm/docstrings.h
nqm/irimager.cpython-38-aarch64-linux-gnu.so
nqm/irimager/irlogger_to_spd.hpp
nqm/irimager/chrono.hpp
nqm/irimager/logger.cpp
nqm/irimager/irimager.cpp
nqm/irimager/irimager_class.hpp
nqm/irimager/logger.hpp
nqm/irimager/irlogger_parser.cpp
nqm/irimager/irlogger_parser.hpp
nqm/irimager/string_ring_buffer.hpp
nqm/irimager/definitions.hpp
nqm/irimager/py.typed
nqm/irimager/irimager_class.cpp
nqm/irimager/__init__.pyi
nqm/irimager/irlogger_to_spd_posix.cpp
nqm_irimager-1.0.0.dist-info/entry_points.txt
nqm_irimager-1.0.0.dist-info/WHEEL
nqm_irimager-1.0.0.dist-info/METADATA
nqm_irimager-1.0.0.dist-info/RECORD
nqm_irimager-1.0.0.dist-info/licenses/docs/licenses.rst
nqm_irimager-1.0.0.dist-info/licenses/LICENSES/MIT.txt
nqm_irimager-1.0.0.dist-info/licenses/LICENSES/BSD-3-Clause.txt
nqm_irimager.libs/libblkid-cb047c19.so.1.1.0
nqm_irimager.libs/libpcre2-8-8701a61e.so.0.7.1
nqm_irimager.libs/libselinux-38862af2.so.1
nqm_irimager.libs/libuuid-364faad9.so.1.3.0
nqm_irimager.libs/libircore-667f586f.so
nqm_irimager.libs/libirimageprocessing-7182ea93.so
nqm_irimager.libs/libirimager-b2c3b0ba.so
nqm_irimager.libs/libmount-ce351e7a.so.1.1.0
nqm_irimager.libs/libudev-7b1031ab.so.1.6.11
nqm_irimager.libs/libusb-1-a410b91d.0.so.0.2.0
