Metadata-Version: 2.1
Name: nqm.irimager
Version: 1.0.0
Summary: Python module for interfacing with EvoCortex IRImagerDirect SDK
Author-Email: Alois Klink <alois@nquiringminds.com>
Classifier: Development Status :: 5 - Production/Stable
Classifier: Topic :: System :: Hardware :: Hardware Drivers
Classifier: Topic :: Multimedia :: Graphics :: Capture :: Digital Camera
Classifier: Intended Audience :: Developers
Classifier: Intended Audience :: Manufacturing
Classifier: Intended Audience :: Science/Research
Classifier: Programming Language :: Python :: 3 :: Only
Classifier: Programming Language :: Python :: 3.8
Classifier: Programming Language :: Python :: 3.9
Classifier: Programming Language :: Python :: 3.10
Classifier: Programming Language :: Python :: 3.11
Requires-Python: <3.12,>=3.8
Requires-Dist: numpy<1.25.0,>=1.24.3
License-File: LICENSES/MIT.txt
License-File: LICENSES/BSD-3-Clause.txt
License-File: docs/licenses.rst
